{
    "created_time": "2023-03-07T06:45:38Z",
    "files": [
        {
            "attachment_folder": "",
            "created_time": "2023-03-07T06:45:38Z",
            "id": "116",
            "modified_time": "2023-03-07T06:45:38Z",
            "name": "skywalking-springboot.md",
            "signature": "25037042539922",
            "tags": [
            ]
        }
    ],
    "folders": [
    ],
    "id": "115",
    "modified_time": "2023-03-07T06:45:38Z",
    "signature": "26931123117458",
    "version": 3
}
